src/config.py
src/main.py
src/services/mongo.py
src/services/users.py
mrvbill_api-0.1.0.dist-info/METADATA
mrvbill_api-0.1.0.dist-info/WHEEL
mrvbill_api-0.1.0.dist-info/RECORD
