Metadata-Version: 2.1
Name: mrvbill-api
Version: 0.1.0
Summary: 
Author: Rares Modure
Author-email: rares.modure@mrv-it.com
Requires-Python: >=3.12,<4.0
Classifier: Programming Language :: Python :: 3
Classifier: Programming Language :: Python :: 3.12
Classifier: Programming Language :: Python :: 3.13
Requires-Dist: auth0-fastapi (>=1.0.0b4,<2.0.0)
Requires-Dist: fastapi[standard] (>=0.115.12,<0.116.0)
Requires-Dist: mangum (>=0.19.0,<0.20.0)
Requires-Dist: motor (>=3.7.1,<4.0.0)
Requires-Dist: pydantic (>=2.11.5,<3.0.0)
Requires-Dist: pydantic-settings (>=2.9.1,<3.0.0)
Requires-Dist: pyjwt[crypto] (>=2.10.1,<3.0.0)
Requires-Dist: pymongo (>=4.13.0,<5.0.0)
Requires-Dist: uvicorn[standard] (>=0.34.3,<0.35.0)
